__init__.py
client.py
service_client.py
datasource/__init__.py
datasource/datasource_client.py
datasource/datasource_type.py
datasource/gcp_authentication.py
datasource/redshift_authentication.py
feature_store/__init__.py
feature_store/feature.py
feature_store/feature_key.py
feature_store/feature_value_type.py
feature_store/featuretable_client.py
inference_server/__init__.py
inference_server/feature_source.py
inference_server/feature_source_type.py
inference_server/inferenceserver_client.py
elemeno_mlops_client-0.0.20.dist-info/AUTHORS.rst
elemeno_mlops_client-0.0.20.dist-info/METADATA
elemeno_mlops_client-0.0.20.dist-info/WHEEL
elemeno_mlops_client-0.0.20.dist-info/top_level.txt
elemeno_mlops_client-0.0.20.dist-info/RECORD
